{

  "Version": "70",

  "ReleaseNotes": "MELHORIAS ENCONTRADAS!",

  "UrlUpdate": "https://raw.githubusercontent.com/clecio81/updates/main/update.json",

  "Sms": "https://raw.githubusercontent.com/sudosalve/GOMESNET_site/master/UrlSms",

  "EmailFeedback": "",

  "UrlContato": "https://wa.me/5566992527471",

  "UrlTermos": "https://sudosalve.github.io/GOMESNET_site/termos.html",

  "CheckUser": "true",

  "Udp": [

    {

      "Porta": "7300"

    }

  ],

  "Servers": [

    {

      "Name": "ELAXI Server 🟢",

      "TYPE": "premium",

      "FLAG": "br.png",

      "ServerIP": "198.161.83.104",

      "CheckUser": "ssh.elaxi.shop:5454/checkUser",

      "ServerPort": "22",

      "SSLPort": "443",

      "USER": "",

      "PASS": ""

    }

  ],

   "Networks": [

        {

            "Name": "VIVO",

            "FLAG": "vivo",

            "Payload": "GET / HTTP/1.1[crlf]Host: ssh.elaxi.shop[crlf]Connection: Upgrade[crlf]Upgrade: Websocket[crlf][crlf]",

            "SNI": "",

            "TlsIP": "",

            "ProxyIP": "198.161.83.104",

            "ProxyPort": "80",

            "Info": "Proxy"

        }
  
  
  ]

}
